{
    "sections": {
        "announcement_bar": {
            "type": "announcement_bar"
        },
        "image_with_text": {
            "type": "image_with_text"
        },
        "steps_with_image": {
            "type": "steps_with_image"
        },
        "faq_1": {
            "type": "faq_1",
            "blocks": {
                "faq-item": {
                    "name": "FAQ Item",
                    "type": "faq-item"
                }
            },
            "block_order": [
                "faq-item"
            ]
        }
    },
    "layout": "theme",
    "wrapper": "main.main-wrapper",
    "order": [
        "announcement_bar",
        "image_with_text",
        "steps_with_image",
        "faq_1"
    ]
}